{"stats":{"minecraft:dropped":{"minecraft:glass_bottle":2},"minecraft:picked_up":{"minecraft:white_banner":1,"minecraft:sugar":1,"minecraft:crossbow":1,"minecraft:saddle":2,"minecraft:emerald":1,"minecraft:glass_bottle":2},"minecraft:killed":{"minecraft:vindicator":5,"minecraft:pillager":3,"minecraft:witch":1,"minecraft:ravager":2},"minecraft:custom":{"minecraft:time_since_rest":8179,"minecraft:crouch_one_cm":1005,"minecraft:play_time":8179,"minecraft:sprint_one_cm":12183,"minecraft:walk_one_cm":19723,"minecraft:raid_trigger":1,"minecraft:sneak_time":464,"minecraft:mob_kills":12,"minecraft:drop":2,"minecraft:jump":70,"minecraft:damage_dealt":3680,"minecraft:leave_game":1,"minecraft:time_since_death":8179,"minecraft:total_world_time":11028,"minecraft:fly_one_cm":97449},"minecraft:used":{"minecraft:netherite_sword":46}},"DataVersion":2975}